zk_crypt_vol_utils
