Metadata-Version: 1.0
Name: zk-luks
Version: 0.5
Summary: Zymkey LUKS Utilities
Home-page: https://zymbit.com
Author: Zymbit, Inc.
Author-email: code@zymbit.com
License: LICENSE.TXT
Platform: UNKNOWN
